miuc/__init__.py
miuc/main.py
miuc/site_processor.py
miuc/utils.py
miuc/web_parser.py
miuc-0.2.8.dist-info/entry_points.txt
miuc-0.2.8.dist-info/LICENSE
miuc-0.2.8.dist-info/METADATA
miuc-0.2.8.dist-info/WHEEL
miuc-0.2.8.dist-info/RECORD
